lambdachain/__init__.py
lambdachain/builtin_hooks.py
lambdachain/functions.py
lambdachain/lambda_chain.py
lambdachain/lambda_identifier.py
lambdachain/utils.py
lambdachain-0.1.dist-info/LICENSE
lambdachain-0.1.dist-info/METADATA
lambdachain-0.1.dist-info/WHEEL
lambdachain-0.1.dist-info/top_level.txt
lambdachain-0.1.dist-info/RECORD
